pramaana/__init__.py
pramaana/cli.py
pramaana/core.py
pramaana/install_completions.py
pramaana/data/completions/_pramaana
pramaana/data/completions/pramaana-completion.bash
pramaana/data/completions/_pramaana
pramaana/data/completions/pramaana-completion.bash
pramaana-1.9.0.dist-info/METADATA
pramaana-1.9.0.dist-info/WHEEL
pramaana-1.9.0.dist-info/entry_points.txt
pramaana-1.9.0.dist-info/RECORD
