Metadata-Version: 2.4
Name: pramaana
Version: 1.9.0
Summary: A minimalist command-line reference manager
Author-email: Abhimanyu Pallavi Sudhir <abhimanyupallavisudhir@gmail.com>
License-Expression: MIT
Requires-Python: >=3.8
Requires-Dist: bibtexparser>=1.4.0
Requires-Dist: pathspec>=0.9.0
Requires-Dist: requests>=2.28.0
